AttendanceProject/Attendance.py
AttendanceProject/AttendanceProjectMain.py
AttendanceProject/ConnectionManager.py
AttendanceProject/DataClasses.py
AttendanceProject/HelperClasses.py
AttendanceProject/__init__.py
AttendanceProject/hodHome.py
AttendanceProject/hodLogin.py
AttendanceProject/hodRegistration.py
AttendanceProject/setup.py
AttendanceProject/studentRegistration.py
AttendanceProject/teacherHome.py
AttendanceProject/teacherLogin.py
AttendanceProject/teacherRegistration.py
AttendanceProject-1.0a0.dist-info/LICENSE
AttendanceProject-1.0a0.dist-info/METADATA
AttendanceProject-1.0a0.dist-info/WHEEL
AttendanceProject-1.0a0.dist-info/top_level.txt
AttendanceProject-1.0a0.dist-info/RECORD
