Metadata-Version: 2.1
Name: AttendanceProject
Version: 1.0a0
Summary: Face Recognition based Attendance System
Home-page: https://github.com/yashsalunke/FRBAS
Author: Yash Salunke
Author-email: yash3a@gmail.com
License: UNKNOWN
Project-URL: Bug Tracker, https://github.com/yashsalunke/FRBAS/issues
Platform: UNKNOWN
Classifier: Programming Language :: Python :: 3
Classifier: License :: OSI Approved :: MIT License
Classifier: Operating System :: OS Independent
Requires-Python: >=3.6
License-File: LICENSE
